odoo/addons/base_rest/README.rst
odoo/addons/base_rest/__init__.py
odoo/addons/base_rest/__manifest__.py
odoo/addons/base_rest/core.py
odoo/addons/base_rest/http.py
odoo/addons/base_rest/tools.py
odoo/addons/base_rest/components/__init__.py
odoo/addons/base_rest/components/service.py
odoo/addons/base_rest/controllers/__init__.py
odoo/addons/base_rest/controllers/api_docs.py
odoo/addons/base_rest/controllers/main.py
odoo/addons/base_rest/models/__init__.py
odoo/addons/base_rest/models/rest_service_registration.py
odoo/addons/base_rest/readme/CONFIGURE.rst
odoo/addons/base_rest/readme/CONTRIBUTORS.rst
odoo/addons/base_rest/readme/DESCRIPTION.rst
odoo/addons/base_rest/readme/HISTORY.rst
odoo/addons/base_rest/readme/ROADMAP.rst
odoo/addons/base_rest/readme/USAGE.rst
odoo/addons/base_rest/static/description/icon.png
odoo/addons/base_rest/static/description/icon.svg
odoo/addons/base_rest/static/description/index.html
odoo/addons/base_rest/static/lib/swagger-ui-3.17.0/favicon-16x16.png
odoo/addons/base_rest/static/lib/swagger-ui-3.17.0/favicon-32x32.png
odoo/addons/base_rest/static/lib/swagger-ui-3.17.0/index.html
odoo/addons/base_rest/static/lib/swagger-ui-3.17.0/oauth2-redirect.html
odoo/addons/base_rest/static/lib/swagger-ui-3.17.0/swagger-ui-bundle.js
odoo/addons/base_rest/static/lib/swagger-ui-3.17.0/swagger-ui-bundle.js.map
odoo/addons/base_rest/static/lib/swagger-ui-3.17.0/swagger-ui-standalone-preset.js
odoo/addons/base_rest/static/lib/swagger-ui-3.17.0/swagger-ui-standalone-preset.js.map
odoo/addons/base_rest/static/lib/swagger-ui-3.17.0/swagger-ui.css
odoo/addons/base_rest/static/lib/swagger-ui-3.17.0/swagger-ui.css.map
odoo/addons/base_rest/static/lib/swagger-ui-3.17.0/swagger-ui.js
odoo/addons/base_rest/static/lib/swagger-ui-3.17.0/swagger-ui.js.map
odoo/addons/base_rest/static/src/js/swagger_ui.js
odoo/addons/base_rest/static/src/less/base_rest.less
odoo/addons/base_rest/tests/__init__.py
odoo/addons/base_rest/tests/common.py
odoo11_addon_base_rest-11.0.2.0.3.dist-info/METADATA
odoo11_addon_base_rest-11.0.2.0.3.dist-info/WHEEL
odoo11_addon_base_rest-11.0.2.0.3.dist-info/top_level.txt
odoo11_addon_base_rest-11.0.2.0.3.dist-info/RECORD
