Metadata-Version: 2.1
Name: odoo11-addon-base-rest
Version: 11.0.2.0.3
Summary: Develop your own high level REST APIs for Odoo thanks to this addon.
Home-page: https://github.com/OCA/rest-framework
Author: ACSONE SA/NV, Odoo Community Association (OCA)
Author-email: support@odoo-community.org
License: LGPL-3
Platform: UNKNOWN
Classifier: Programming Language :: Python
Classifier: Framework :: Odoo
Classifier: License :: OSI Approved :: GNU Lesser General Public License v3 (LGPLv3)
Classifier: Development Status :: 4 - Beta
Requires-Python: >=2.7, !=3.0.*, !=3.1.*, !=3.2.*, !=3.3.*, !=3.4.*
Requires-Dist: cerberus
Requires-Dist: odoo11-addon-component
Requires-Dist: odoo (<11.1dev,>=11.0a)
Requires-Dist: parse-accept-language
Requires-Dist: pyquerystring
